drafts/__about__.py
drafts/__init__.py
drafts/defaults.py
drafts/generators.py
pelican_drafts-0.1.1.dist-info/LICENSE
pelican_drafts-0.1.1.dist-info/METADATA
pelican_drafts-0.1.1.dist-info/WHEEL
pelican_drafts-0.1.1.dist-info/top_level.txt
pelican_drafts-0.1.1.dist-info/RECORD
