Metadata-Version: 2.1
Name: pelican-drafts
Version: 0.1.1
Summary: Add a browsable drafts listing to your Pelican website
Home-page: https://github.com/noirbizarre/pelican-drafts
Author: Axel Haustant
Author-email: noirbizarre+github@gmail.com
License: MIT
Keywords: pelican,draft
Platform: UNKNOWN
Classifier: Development Status :: 3 - Alpha
Classifier: Programming Language :: Python
Classifier: Environment :: Web Environment
Classifier: Operating System :: OS Independent
Classifier: Intended Audience :: Developers
Classifier: Topic :: System :: Software Distribution
Classifier: Programming Language :: Python
Classifier: Programming Language :: Python :: 3
Classifier: Programming Language :: Python :: 3.7
Classifier: Programming Language :: Python :: 3.8
Classifier: Topic :: Software Development :: Libraries :: Python Modules
Classifier: License :: OSI Approved :: MIT License
Requires-Python: >=3.7
Requires-Dist: pelican (>=4.2.0)
Provides-Extra: qa
Requires-Dist: pytest-cov ; extra == 'qa'
Requires-Dist: flake8 ; extra == 'qa'
Provides-Extra: test
Requires-Dist: pytest (<5.4) ; extra == 'test'
